{"9":[1,1,1,13],"17":[1,1,1,14],"25":[3,14,3,21],"33":[3,22,3,28],"41":[3,14,3,29],"49":[3,14,3,29],"57":[3,14,3,29],"65":[5,17,5,21],"73":[5,27,5,36],"81":[5,38,5,43],"89":[5,17,5,44],"91":[5,17,5,26],"97":[5,17,5,44],"105":[5,17,5,44],"113":[6,16,6,20],"121":[6,26,6,33],"129":[6,35,6,46],"137":[6,16,6,47],"139":[6,16,6,25],"145":[6,16,6,47],"153":[6,16,6,47],"161":[7,13,7,17],"169":[7,23,7,30],"177":[7,32,7,40],"185":[7,13,7,41],"187":[7,13,7,22],"193":[7,13,7,41],"201":[7,13,7,41],"209":[8,17,8,21],"217":[8,27,8,34],"225":[8,36,8,45],"233":[8,17,8,46],"235":[8,17,8,26],"241":[8,17,8,46],"249":[8,17,8,46],"257":[9,16,9,20],"265":[9,26,9,33],"273":[9,35,9,48],"281":[9,16,9,49],"283":[9,16,9,25],"289":[9,16,9,49],"297":[9,16,9,49],"305":[10,24,10,28],"313":[10,34,10,41],"321":[10,43,10,57],"329":[10,24,10,58],"331":[10,24,10,33],"337":[10,24,10,58],"345":[10,24,10,58],"353":[11,24,11,28],"361":[11,34,11,41],"369":[11,43,11,65],"377":[11,24,11,66],"379":[11,24,11,33],"385":[11,24,11,66],"393":[11,24,11,66],"401":[12,21,12,25],"409":[12,31,12,38],"417":[12,40,12,54],"425":[12,21,12,55],"427":[12,21,12,30],"433":[12,21,12,55],"441":[12,21,12,55],"449":[14,1,14,8],"457":[15,2,15,9],"465":[16,2,16,8],"473":[17,2,17,5],"481":[18,2,18,9],"489":[19,2,19,8],"497":[20,2,20,16],"505":[21,2,21,16],"513":[22,2,22,13],"521":[14,17,23,2],"529":[14,1,23,2],"537":[14,1,23,3],"545":[25,1,25,8],"553":[25,29,25,88],"561":[25,1,25,88],"569":[25,1,25,89],"577":[26,1,26,8],"585":[26,28,26,63],"593":[26,1,26,63],"601":[26,1,26,64],"609":[1,1,27,1],"617":[1,1,27,1],"625":[1,1,27,1],"633":[1,1,27,1],"641":[1,1,27,1],"649":[1,1,27,1],"657":[1,1,27,1],"665":[1,1,27,1],"673":[1,1,27,1],"681":[1,1,27,1],"689":[1,1,27,1],"697":[1,1,27,1],"nBranches":0,"originalCodeFileName":"/workspaces/nodebb-spring-26-team-f1/src/constants.js","instrumentedCodeFileName":"/workspaces/nodebb-spring-26-team-f1/src/constants_jalangi_.js","code":"'use strict';\n\nconst path = require('path');\n\nconst baseDir = path.join(__dirname, '../');\nconst loader = path.join(baseDir, 'loader.js');\nconst app = path.join(baseDir, 'app.js');\nconst pidfile = path.join(baseDir, 'pidfile');\nconst config = path.join(baseDir, 'config.json');\nconst currentPackage = path.join(baseDir, 'package.json');\nconst installPackage = path.join(baseDir, 'install/package.json');\nconst nodeModules = path.join(baseDir, 'node_modules');\n\nexports.paths = {\n\tbaseDir,\n\tloader,\n\tapp,\n\tpidfile,\n\tconfig,\n\tcurrentPackage,\n\tinstallPackage,\n\tnodeModules,\n};\n\nexports.pluginNamePattern = /^(@[\\w-]+\\/)?nodebb-(theme|plugin|widget|rewards)-[\\w-]+$/;\nexports.themeNamePattern = /^(@[\\w-]+\\/)?nodebb-theme-[\\w-]+$/;\n"}